README.md
setup.py
chronopy/Clock.py
chronopy/__init__.py
chronopy.egg-info/PKG-INFO
chronopy.egg-info/SOURCES.txt
chronopy.egg-info/dependency_links.txt
chronopy.egg-info/top_level.txt