Metadata-Version: 2.1
Name: chronopy
Version: 0.1.3
Summary: A simple Python package to measure execution time
Home-page: https://github.com/giacomopiccinini/Clock
Author: Giacomo Piccinini
Author-email: giacomo@gemmo.ai
License: MIT
Platform: UNKNOWN
Classifier: Development Status :: 1 - Planning
Classifier: Intended Audience :: Science/Research
Classifier: Programming Language :: Python :: 3.9
